mtllm_python/__init__.py
mtllm_python-0.1.0.dist-info/LICENSE
mtllm_python-0.1.0.dist-info/METADATA
mtllm_python-0.1.0.dist-info/WHEEL
mtllm_python-0.1.0.dist-info/RECORD
