Metadata-Version: 2.1
Name: mtllm-python
Version: 0.1.0
Summary: Python implementation of the MTLLM to be used in Python Projects
License: MIT
Keywords: MTLLM,Python,NLP,Language Model
Author: chandralegend
Author-email: irugalbandarachandra@gmail.com
Requires-Python: >=3.12,<4.0
Classifier: License :: OSI Approved :: MIT License
Classifier: Programming Language :: Python :: 3
Classifier: Programming Language :: Python :: 3.12
Requires-Dist: mtllm (>=0.1.7,<0.2.0)
